[{
  "_id": {
    "$oid": "645429659f8fa2215bcc338e"
  },
  "nombre": "julian",
  "apellido": "lopez",
  "correo": "julian@unah.hn",
  "password": "julian8888",
  "direccion": "residencial plaza",
  "nombreTarjeta": "julian lopez",
  "numeroTarjeta": "0201489026708977",
  "expira": "09",
  "mes": "09",
  "cvv": "091",
  "longitud": "-87.2153088",
  "latitud": "14.0804096",
  "ordenes": [
    {
      "nombreProducto": "coca cola",
      "descripcion": "coca cola en lata",
      "cantidad": 2,
      "precio": 25
    },
    {
      "nombreProducto": "Gel de manos",
      "descripcion": "Gel para el cuidado de higiene",
      "cantidad": 3,
      "precio": 90
    }
  ]
},{
  "_id": {
    "$oid": "645429659f8fa2215bcc338f"
  },
  "nombre": "marcela",
  "apellido": "castillo",
  "correo": "marce@unah.hn",
  "password": "marce8888",
  "direccion": "residencial plaza",
  "nombreTarjeta": "marcela lopez",
  "numeroTarjeta": "0221989934556788",
  "expira": "05",
  "mes": "01",
  "cvv": "054",
  "longitud": "-87.2153088",
  "latitud": "14.0804096",
  "ordenes": [
    {
      "nombreProducto": "clasica",
      "descripcion": "Pizza clasica de peperoni",
      "cantidad": 2,
      "precio": 99
    },
    {
      "nombreProducto": "camisa",
      "descripcion": "Camisa de cuello casual",
      "cantidad": 3,
      "precio": 350
    }
  ]
},{
  "_id": {
    "$oid": "64574a24498df1aaa87ef61e"
  },
  "nombre": "pedro",
  "apellido": "gonzales",
  "correo": "pedro@unah.hn",
  "password": "pedro1234",
  "__v": 0
}]